polars_mcp.py
guides/contexts.md
guides/expressions.md
guides/lazy-api.md
guides/pandas-to-polars.md
polars_mcp-0.2.1.dist-info/METADATA
polars_mcp-0.2.1.dist-info/WHEEL
polars_mcp-0.2.1.dist-info/entry_points.txt
polars_mcp-0.2.1.dist-info/licenses/LICENSE
polars_mcp-0.2.1.dist-info/RECORD
