Metadata-Version: 2.4
Name: polars-mcp
Version: 0.2.1
Summary: MCP server providing Polars API reference and usage guides for efficient Polars query development
License-Expression: MIT
License-File: LICENSE
Requires-Python: >=3.10
Requires-Dist: mcp>=1.0.0
Requires-Dist: polars
